acinf/__main__.py
acinf-0.0.2.dist-info/LICENSE.txt
acinf-0.0.2.dist-info/METADATA
acinf-0.0.2.dist-info/WHEEL
acinf-0.0.2.dist-info/entry_points.txt
acinf-0.0.2.dist-info/top_level.txt
acinf-0.0.2.dist-info/RECORD
