Metadata-Version: 2.1
Name: acinf
Version: 0.0.2
Summary: AC Infinity Controller 69 Pro command-line and API
Project-URL: homepage, https://github.com/jquast/acinf
License-File: LICENSE.txt
